fd/__about__.py
fd/__init__.py
fd/cli.py
fd/config.py
fd/dir_entry.py
fd/error.py
fd/exit_codes.py
fd/filesystem.py
fd/main.py
fd/output.py
fd/regex_helper.py
fd/walk.py
fd/filter/__init__.py
fd/filter/size.py
fd_python-0.1.0.dist-info/METADATA
fd_python-0.1.0.dist-info/WHEEL
fd_python-0.1.0.dist-info/entry_points.txt
fd_python-0.1.0.dist-info/licenses/LICENSE.txt
fd_python-0.1.0.dist-info/RECORD
