Metadata-Version: 2.3
Name: fd-python
Version: 0.1.0
Summary: A Python based reimplementation of fd
Project-URL: repository, https://github.com/borsattoz/fd-python
License: MIT License
License-File: LICENSE.txt
Keywords: cli,command-line,filesystem,python,regex,search,terminal,tool
Classifier: Development Status :: 4 - Beta
Classifier: Programming Language :: Python
Classifier: Programming Language :: Python :: 3.8
Classifier: Programming Language :: Python :: 3.9
Classifier: Programming Language :: Python :: 3.10
Classifier: Programming Language :: Python :: 3.11
Classifier: Programming Language :: Python :: 3.12
Classifier: Programming Language :: Python :: Implementation :: CPython
Classifier: Programming Language :: Python :: Implementation :: PyPy
Requires-Python: >=3.8
Requires-Dist: ignore-python~=0.1.2
Requires-Dist: regex~=2024.7.24
Requires-Dist: wcmatch~=9.0
